lazy_mysql/__init__.py
lazy_mysql/executor.py
lazy_mysql/sql_config.py
lazy_mysql/tools/__init__.py
lazy_mysql/tools/result_formatter.py
lazy_mysql/tools/sql_utils.py
lazy_mysql/tools/table_export.py
lazy_mysql/tools/where_clause.py
lazy_mysql/utils/__init__.py
lazy_mysql/utils/connect.py
lazy_mysql/utils/delete.py
lazy_mysql/utils/insert.py
lazy_mysql/utils/select.py
lazy_mysql/utils/update/__init__.py
lazy_mysql/utils/update/batch_update.py
lazy_mysql/utils/update/update.py
lazy_mysql-0.4.4.dist-info/licenses/LICENSE
lazy_mysql-0.4.4.dist-info/METADATA
lazy_mysql-0.4.4.dist-info/WHEEL
lazy_mysql-0.4.4.dist-info/top_level.txt
lazy_mysql-0.4.4.dist-info/RECORD
