Metadata-Version: 2.4
Name: lazy_mysql
Version: 0.4.4
Summary: A lazy MySQL client for Python that simplifies database operations with intuitive methods for CRUD operations, automatic connection management, and result formatting. Features include easy-to-use SELECT, INSERT, UPDATE, DELETE operations with pandas DataFrame support, where clause builders, and table export capabilities.
Home-page: https://github.com/tinycen/lazy_mysql
Author: tinycen
Author-email: sky_ruocen@qq.com
Classifier: Programming Language :: Python :: 3
Classifier: License :: OSI Approved :: MIT License
Classifier: Operating System :: OS Independent
Requires-Python: >=3.10
License-File: LICENSE
Requires-Dist: mysql-connector-python>=9.4.0
Requires-Dist: pandas>=2.3.1
Dynamic: author
Dynamic: author-email
Dynamic: classifier
Dynamic: description
Dynamic: description-content-type
Dynamic: home-page
Dynamic: license-file
Dynamic: requires-dist
Dynamic: requires-python
Dynamic: summary
